PrettyDF/__init__.py
PrettyDF/credits.py
PrettyDF/main.py
PrettyDF-1.1.4.dist-info/METADATA
PrettyDF-1.1.4.dist-info/WHEEL
PrettyDF-1.1.4.dist-info/entry_points.txt
PrettyDF-1.1.4.dist-info/top_level.txt
PrettyDF-1.1.4.dist-info/RECORD
