Metadata-Version: 2.1
Name: PrettyDF
Version: 1.1.4
Summary: Pretty Print DataFrames
Author: DawnSaju
Author-email: dawnsajubusiness@gmail.com
Classifier: Programming Language :: Python :: 3
Requires-Dist: pyfiglet
Requires-Dist: asciimatics
Requires-Dist: pandas
Requires-Dist: tabulate
Requires-Dist: matplotlib
